<?xml version="1.0" encoding="UTF-8"?>
<config date="1601493254682" transient="false">
	<site updateable="true" url="file:/Users/malinda/.p2/pool/" enabled="true" policy="MANAGED-ONLY">
		<feature id="org.eclipse.oomph.setup.workingsets" version="1.14.0.v20200815-0620" url="features/org.eclipse.oomph.setup.workingsets_1.14.0.v20200815-0620/">
		</feature>
		<feature id="org.eclipse.rcp" version="4.16.0.v20200604-0951" url="features/org.eclipse.rcp_4.16.0.v20200604-0951/">
		</feature>
		<feature id="org.eclipse.mylyn.monitor" version="3.25.1.v20200511-1958" url="features/org.eclipse.mylyn.monitor_3.25.1.v20200511-1958/" plugin-identifier="org.eclipse.mylyn.commons.core">
		</feature>
		<feature id="org.eclipse.jgit.http.apache" version="5.8.0.202006091008-r" url="features/org.eclipse.jgit.http.apache_5.8.0.202006091008-r/">
		</feature>
		<feature id="org.eclipse.emf.common" version="2.19.0.v20200324-0932" url="features/org.eclipse.emf.common_2.19.0.v20200324-0932/">
		</feature>
		<feature id="org.eclipse.eclemma.feature" version="3.1.3.202003132300" url="features/org.eclipse.eclemma.feature_3.1.3.202003132300/" plugin-identifier="org.eclipse.eclemma.ui">
		</feature>
		<feature id="org.eclipse.help" version="2.3.200.v20200604-0540" url="features/org.eclipse.help_2.3.200.v20200604-0540/" plugin-identifier="org.eclipse.help.base">
		</feature>
		<feature id="org.eclipse.ecf.core.ssl.feature" version="1.1.400.v20200317-1602" url="features/org.eclipse.ecf.core.ssl.feature_1.1.400.v20200317-1602/">
		</feature>
		<feature id="org.eclipse.equinox.p2.extras.feature" version="1.4.800.v20200511-1530" url="features/org.eclipse.equinox.p2.extras.feature_1.4.800.v20200511-1530/">
		</feature>
		<feature id="org.eclipse.ecf.filetransfer.feature" version="3.14.800.v20200317-1602" url="features/org.eclipse.ecf.filetransfer.feature_3.14.800.v20200317-1602/">
		</feature>
		<feature id="org.eclipse.mylyn_feature" version="3.25.1.v20200514-1748" url="features/org.eclipse.mylyn_feature_3.25.1.v20200514-1748/" plugin-identifier="org.eclipse.mylyn.tasks.core">
		</feature>
		<feature id="org.eclipse.m2e.feature" version="1.16.0.20200610-1735" url="features/org.eclipse.m2e.feature_1.16.0.20200610-1735/" plugin-identifier="org.eclipse.m2e.core">
		</feature>
		<feature id="org.eclipse.mylyn.discovery" version="3.25.1.v20200511-1958" url="features/org.eclipse.mylyn.discovery_3.25.1.v20200511-1958/" plugin-identifier="org.eclipse.mylyn.commons.core">
		</feature>
		<feature id="org.eclipse.epp.mpc" version="1.8.3.v20200526-1554" url="features/org.eclipse.epp.mpc_1.8.3.v20200526-1554/" plugin-identifier="org.eclipse.epp.mpc.ui">
		</feature>
		<feature id="org.eclipse.mylyn.commons.notifications" version="1.17.1.v20200511-1958" url="features/org.eclipse.mylyn.commons.notifications_1.17.1.v20200511-1958/" plugin-identifier="org.eclipse.mylyn.commons.core">
		</feature>
		<feature id="org.eclipse.egit" version="5.8.0.202006091008-r" url="features/org.eclipse.egit_5.8.0.202006091008-r/">
		</feature>
		<feature id="org.eclipse.platform" version="4.16.0.v20200604-0951" url="features/org.eclipse.platform_4.16.0.v20200604-0951/">
		</feature>
		<feature id="org.eclipse.mylyn.wikitext.editors_feature" version="3.0.36.202002070035" url="features/org.eclipse.mylyn.wikitext.editors_feature_3.0.36.202002070035/" plugin-identifier="org.eclipse.mylyn.wikitext">
		</feature>
		<feature id="org.eclipse.oomph.setup.core" version="1.18.0.v20200901-1012" url="features/org.eclipse.oomph.setup.core_1.18.0.v20200901-1012/">
		</feature>
		<feature id="org.eclipse.oomph.setup" version="1.18.0.v20200901-1012" url="features/org.eclipse.oomph.setup_1.18.0.v20200901-1012/">
		</feature>
		<feature id="org.eclipse.ecf.core.feature" version="1.5.600.v20200317-1602" url="features/org.eclipse.ecf.core.feature_1.5.600.v20200317-1602/">
		</feature>
		<feature id="org.eclipse.equinox.p2.rcp.feature" version="1.4.800.v20200602-1138" url="features/org.eclipse.equinox.p2.rcp.feature_1.4.800.v20200602-1138/">
		</feature>
		<feature id="org.eclipse.e4.rcp" version="4.16.0.v20200604-0951" url="features/org.eclipse.e4.rcp_4.16.0.v20200604-0951/">
		</feature>
		<feature id="org.eclipse.emf.ecore" version="2.22.0.v20200519-1135" url="features/org.eclipse.emf.ecore_2.22.0.v20200519-1135/">
		</feature>
		<feature id="org.eclipse.jdt" version="3.18.400.v20200604-0540" url="features/org.eclipse.jdt_3.18.400.v20200604-0540/">
		</feature>
		<feature id="org.eclipse.equinox.p2.discovery.feature" version="1.2.600.v20200521-1852" url="features/org.eclipse.equinox.p2.discovery.feature_1.2.600.v20200521-1852/">
		</feature>
		<feature id="org.eclipse.jgit.ssh.apache" version="5.8.0.202006091008-r" url="features/org.eclipse.jgit.ssh.apache_5.8.0.202006091008-r/">
		</feature>
		<feature id="org.eclipse.oomph.setup.pde" version="1.13.0.v20200624-1156" url="features/org.eclipse.oomph.setup.pde_1.13.0.v20200624-1156/">
		</feature>
		<feature id="org.eclipse.userstorage" version="1.2.0.v20191120-1614" url="features/org.eclipse.userstorage_1.2.0.v20191120-1614/">
		</feature>
		<feature id="org.eclipse.equinox.p2.user.ui" version="2.4.800.v20200602-1138" url="features/org.eclipse.equinox.p2.user.ui_2.4.800.v20200602-1138/">
		</feature>
		<feature id="org.eclipse.jgit.gpg.bc" version="5.8.0.202006091008-r" url="features/org.eclipse.jgit.gpg.bc_5.8.0.202006091008-r/">
		</feature>
		<feature id="org.eclipse.epp.package.java.feature" version="4.16.0.20200615-1200" url="features/org.eclipse.epp.package.java.feature_4.16.0.20200615-1200/" plugin-identifier="org.eclipse.epp.package.java">
		</feature>
		<feature id="org.eclipse.wildwebdeveloper.xml.feature" version="0.10.0.202006021616" url="features/org.eclipse.wildwebdeveloper.xml.feature_0.10.0.202006021616/">
		</feature>
		<feature id="org.eclipse.mylyn.commons.repositories" version="1.17.1.v20200511-1958" url="features/org.eclipse.mylyn.commons.repositories_1.17.1.v20200511-1958/" plugin-identifier="org.eclipse.mylyn.commons.core">
		</feature>
		<feature id="org.eclipse.equinox.p2.core.feature" version="1.6.600.v20200511-1530" url="features/org.eclipse.equinox.p2.core.feature_1.6.600.v20200511-1530/">
		</feature>
		<feature id="org.eclipse.tips.feature" version="0.2.1000.v20200522-1444" url="features/org.eclipse.tips.feature_0.2.1000.v20200522-1444/">
		</feature>
		<feature id="org.eclipse.m2e.sse.ui.feature" version="1.16.0.20200514-2159" url="features/org.eclipse.m2e.sse.ui.feature_1.16.0.20200514-2159/">
		</feature>
		<feature id="org.eclipse.oomph.setup.git" version="1.18.0.v20200624-1156" url="features/org.eclipse.oomph.setup.git_1.18.0.v20200624-1156/">
		</feature>
		<feature id="org.eclipse.ecf.filetransfer.httpclient45.feature" version="1.0.400.v20200522-1203" url="features/org.eclipse.ecf.filetransfer.httpclient45.feature_1.0.400.v20200522-1203/">
		</feature>
		<feature id="org.eclipse.epp.package.common.feature" version="4.16.0.20200615-1200" url="features/org.eclipse.epp.package.common.feature_4.16.0.20200615-1200/">
		</feature>
		<feature id="org.eclipse.oomph.setup.jdt" version="1.16.0.v20200624-1156" url="features/org.eclipse.oomph.setup.jdt_1.16.0.v20200624-1156/">
		</feature>
		<feature id="org.eclipse.ecf.filetransfer.ssl.feature" version="1.1.300.v20200317-1602" url="features/org.eclipse.ecf.filetransfer.ssl.feature_1.1.300.v20200317-1602/">
		</feature>
		<feature id="org.eclipse.mylyn.wikitext_feature" version="3.0.36.202002070035" url="features/org.eclipse.mylyn.wikitext_feature_3.0.36.202002070035/" plugin-identifier="org.eclipse.mylyn.wikitext">
		</feature>
		<feature id="org.eclipse.mylyn.commons" version="3.25.1.v20200511-1958" url="features/org.eclipse.mylyn.commons_3.25.1.v20200511-1958/" plugin-identifier="org.eclipse.mylyn.commons.core">
		</feature>
		<feature id="org.eclipse.buildship" version="3.1.4.v20200326-1743" url="features/org.eclipse.buildship_3.1.4.v20200326-1743/" plugin-identifier="org.eclipse.buildship.branding">
		</feature>
		<feature id="org.eclipse.m2e.lemminx.feature" version="1.16.0.20200609-1359" url="features/org.eclipse.m2e.lemminx.feature_1.16.0.20200609-1359/">
		</feature>
		<feature id="org.eclipse.m2e.logback.feature" version="1.16.0.20200318-1040" url="features/org.eclipse.m2e.logback.feature_1.16.0.20200318-1040/" plugin-identifier="org.eclipse.m2e.logback.configuration">
		</feature>
		<feature id="org.eclipse.oomph.targlets" version="1.16.0.v20200624-1156" url="features/org.eclipse.oomph.targlets_1.16.0.v20200624-1156/">
		</feature>
		<feature id="org.eclipse.jgit.ssh.jsch" version="5.8.0.202006091008-r" url="features/org.eclipse.jgit.ssh.jsch_5.8.0.202006091008-r/">
		</feature>
		<feature id="org.eclipse.jgit" version="5.8.0.202006091008-r" url="features/org.eclipse.jgit_5.8.0.202006091008-r/">
		</feature>
		<feature id="org.eclipse.pde.api.tools.ee.feature" version="1.0.700.v20190929-1236" url="features/org.eclipse.pde.api.tools.ee.feature_1.0.700.v20190929-1236/">
		</feature>
		<feature id="org.eclipse.oomph.p2" version="1.17.0.v20200820-0414" url="features/org.eclipse.oomph.p2_1.17.0.v20200820-0414/">
		</feature>
		<feature id="org.eclipse.mylyn.commons.identity" version="1.17.1.v20200511-1958" url="features/org.eclipse.mylyn.commons.identity_1.17.1.v20200511-1958/" plugin-identifier="org.eclipse.mylyn.commons.core">
		</feature>
		<feature id="org.eclipse.oomph.setup.targlets" version="1.14.0.v20200624-1156" url="features/org.eclipse.oomph.setup.targlets_1.14.0.v20200624-1156/">
		</feature>
	</site>
</config>
